toondb/__init__.py
toondb/database.py
toondb/errors.py
toondb/ipc_client.py
toondb/query.py
toondb_client-0.1.0.dist-info/METADATA
toondb_client-0.1.0.dist-info/WHEEL
toondb_client-0.1.0.dist-info/top_level.txt
toondb_client-0.1.0.dist-info/RECORD
