Metadata-Version: 2.4
Name: toondb-client
Version: 0.1.0
Summary: ToonDB is an AI-native database with token-optimized output, O(|path|) lookups, built-in vector search, and durable transactions.
Author-email: Sushanth <sushanth@toondb.dev>
Maintainer-email: Sushanth <sushanth@toondb.dev>
License: Apache-2.0
Project-URL: Homepage, https://github.com/toondb/toondb
Project-URL: Repository, https://github.com/toondb/toondb
Project-URL: Documentation, https://github.com/toondb/toondb/tree/main/toondb-python-sdk
Project-URL: Bug Tracker, https://github.com/toondb/toondb/issues
Keywords: database,llm,ai,vector-search,embedded,key-value,toondb,context-retrieval,transactions
Classifier: Development Status :: 4 - Beta
Classifier: Intended Audience :: Developers
Classifier: License :: OSI Approved :: Apache Software License
Classifier: Programming Language :: Python :: 3
Classifier: Programming Language :: Python :: 3.9
Classifier: Programming Language :: Python :: 3.10
Classifier: Programming Language :: Python :: 3.11
Classifier: Programming Language :: Python :: 3.12
Classifier: Programming Language :: Python :: 3.13
Classifier: Programming Language :: Rust
Classifier: Topic :: Database
Classifier: Topic :: Database :: Database Engines/Servers
Classifier: Topic :: Scientific/Engineering :: Artificial Intelligence
Classifier: Operating System :: MacOS
Classifier: Operating System :: POSIX :: Linux
Requires-Python: >=3.9
Provides-Extra: dev
Requires-Dist: pytest>=7.0; extra == "dev"
Requires-Dist: pytest-cov>=4.0; extra == "dev"
Requires-Dist: faker>=18.0; extra == "dev"
